dstructure/BTree.py
dstructure/DCLL.py
dstructure/DLL.py
dstructure/Graph.py
dstructure/HashMap.py
dstructure/MaxHeap.py
dstructure/MinHeap.py
dstructure/Queue.py
dstructure/SCLL.py
dstructure/SLL.py
dstructure/Stack.py
dstructure/__init__.py
dstructure/algo.py
dstructure-0.1.5.dist-info/LICENCE.txt
dstructure-0.1.5.dist-info/METADATA
dstructure-0.1.5.dist-info/WHEEL
dstructure-0.1.5.dist-info/top_level.txt
dstructure-0.1.5.dist-info/RECORD
