Metadata-Version: 2.1
Name: dstructure
Version: 0.1.5
Summary: Data Structure
Home-page: UNKNOWN
Author: Vivek Pisal
Author-email: vivekpisal12345@gmail.com
License: UNKNOWN
Platform: UNKNOWN
Classifier: Programming Language :: Python :: 3
Classifier: License :: OSI Approved :: MIT License
Classifier: Operating System :: OS Independent
Requires-Python: >=3.6
